LICENSE
README.md
setup.py
hjmlyy/__init__.py
hjmlyy/facecat.py
hjmlyy/facecatcpp.dll
hjmlyy/kline.py
hjmlyy.egg-info/PKG-INFO
hjmlyy.egg-info/SOURCES.txt
hjmlyy.egg-info/dependency_links.txt
hjmlyy.egg-info/top_level.txt