Metadata-Version: 2.1
Name: hjmlyy
Version: 1.1
Summary: A description of your package
Home-page: https://github.com/yourusername/my_package
Author: Tao De
Author-email: your.email@example.com
Classifier: Programming Language :: Python :: 3
Classifier: License :: OSI Approved :: MIT License
Classifier: Operating System :: OS Independent
Requires-Python: >=3.6
License-File: LICENSE
